matrix_math_group_21/__init__.py
matrix_math_group_21/core.py
matrix_math_group21-0.1.0.dist-info/METADATA
matrix_math_group21-0.1.0.dist-info/WHEEL
matrix_math_group21-0.1.0.dist-info/top_level.txt
matrix_math_group21-0.1.0.dist-info/RECORD
